winsandbox/__init__.py
winsandbox/cli.py
winsandbox/folder_mapper.py
winsandbox/launch.py
winsandbox/sandbox.py
winsandbox/target.py
winsandbox/config/__init__.py
winsandbox/config/config.py
winsandbox/config/config_genereator.py
winsandbox/session/__init__.py
winsandbox/session/offline_session.py
winsandbox/session/online_session.py
winsandbox/shell_extension/__init__.py
winsandbox/shell_extension/open_sandboxed.py
winsandbox/shell_extension/sandbox.ico
winsandbox/utils/__init__.py
winsandbox/utils/dev_environment.py
winsandbox/utils/errors.py
winsandbox/utils/file.py
winsandbox/utils/path.py
winsandbox/utils/sandbox_feature_state.py
winsandbox/utils/venv.py
pywinsandbox-1.4.0.dist-info/LICENSE
pywinsandbox-1.4.0.dist-info/METADATA
pywinsandbox-1.4.0.dist-info/WHEEL
pywinsandbox-1.4.0.dist-info/entry_points.txt
pywinsandbox-1.4.0.dist-info/top_level.txt
pywinsandbox-1.4.0.dist-info/RECORD
