Metadata-Version: 2.1
Name: pywinsandbox
Version: 1.4.0
Summary: Python Utilities for Windows Sandbox
Home-page: https://github.com/karkason/pywinsandbox
Author: Yiftach Karkason
Author-email: ykarkason@gmail.com
License: MIT
Platform: UNKNOWN
Requires-Dist: yattag
Requires-Dist: rpyc
Requires-Dist: cached-property
Requires-Dist: recordclass
Requires-Dist: IPython
Requires-Dist: wmi
Provides-Extra: test
Requires-Dist: pytest ; extra == 'test'
